proofaday/__init__.py
proofaday/__main__.py
proofaday/cli_util.py
proofaday/constants.py
proofaday/daemon.py
proofaday/daemon_cli.py
proofaday/message.py
proofaday/proof.py
proofaday/proofaday.py
proofaday/status.py
proofaday/syms.py
proofaday-0.2.18.dist-info/LICENSE
proofaday-0.2.18.dist-info/METADATA
proofaday-0.2.18.dist-info/WHEEL
proofaday-0.2.18.dist-info/entry_points.txt
proofaday-0.2.18.dist-info/RECORD
