Metadata-Version: 2.1
Name: proofaday
Version: 0.2.18
Summary: Print random proofs from ProofWiki
Home-page: https://github.com/whonore/proofaday
License: MIT
Author: Wolf Honoré
Author-email: wolfhonore@gmail.com
Requires-Python: >=3.6.2,<4.0.0
Classifier: Development Status :: 4 - Beta
Classifier: Environment :: Console
Classifier: License :: OSI Approved :: MIT License
Classifier: Natural Language :: English
Classifier: Operating System :: MacOS
Classifier: Operating System :: POSIX :: Linux
Classifier: Programming Language :: Python :: 3
Classifier: Programming Language :: Python :: 3.7
Classifier: Programming Language :: Python :: 3.8
Classifier: Programming Language :: Python :: 3.9
Classifier: Programming Language :: Python :: 3.10
Classifier: Programming Language :: Python :: 3.11
Classifier: Programming Language :: Python :: 3 :: Only
Requires-Dist: beautifulsoup4 (>=4.9.0,<5.0.0)
Requires-Dist: click (>=8.0.0,<9.0.0)
Requires-Dist: platformdirs (>=2.3.0,<3.0.0)
Requires-Dist: pylatexenc (>=2.8,<3.0)
Requires-Dist: python-daemon (>=2.2.0,<3.0.0)
Requires-Dist: requests (>=2.24.0,<3.0.0)
Project-URL: Repository, https://github.com/whonore/proofaday
